{
  "welcome": "Willkommen",
  "settings": "Einstellungen",
  "darkMode": "Dunkelmodus",
  "notifications": "Benachrichtigungen",
  "language": "Sprache",
  "logout": "Abmelden",
  "selectLanguage": "Sprache wählen",
  "reports": "Berichte",
  "orders": "Bestellungen",
  "space": "Platz",
  "expiry": "Ablauf",
  "products": "Produkte",
  "Robots": "Roboter",
  "Profile": "Profil",
  "Section": "Abschnitt",
  "Price": "Preis",
  "Quantity": "Menge",
  "inflow": "Zufluss",
  "current": "Aktuell",
  "outflow": "Abfluss",
  "total": "Gesamt",
  "home": "Startseite",
  "cart": "Warenkorb",
  "time": "Zeit",
  "name": "Name",
  "addToCart": "In den Warenkorb legen",
  "productDetails": "Produktdetails",
  "email": "E-Mail-Adresse",
  "confirmEmail": "E-Mail-Adresse bestätigen",
  "password": "Passwort",
  "confirmPassword": "Passwort bestätigen",
  "enterPicture": "Bild hinzufügen",
  "create": "Erstellen",
  "numberOfSections": "Anzahl der Abschnitte",
  "numberOfRobots": "Anzahl der Roboter",
  "capacityOfSection": "Kapazität des Abschnitts",
  "maintenanceDateOfRobot": "Wartungsdatum des Roboters",
  "signUp": "Registrieren",
  "login": "Anmelden",
  "createNewUser": "Neuen Benutzer erstellen",
  "cancel": "Abbrechen",
    "submit": "Einreichen",
    "inputData": "Eingabedaten"
}
